CHANGES.txt
README.txt
setup.cfg
setup.py
plone/__init__.py
plone.introspector.egg-info/PKG-INFO
plone.introspector.egg-info/SOURCES.txt
plone.introspector.egg-info/dependency_links.txt
plone.introspector.egg-info/entry_points.txt
plone.introspector.egg-info/namespace_packages.txt
plone.introspector.egg-info/not-zip-safe
plone.introspector.egg-info/requires.txt
plone.introspector.egg-info/top_level.txt
plone/introspector/__init__.py
plone/introspector/configure.zcml
plone/introspector/interfaces.py
plone/introspector/monkey.py
plone/introspector/workflowinfo.py
plone/introspector/browser/__init__.py
plone/introspector/browser/adapter.pt
plone/introspector/browser/browse_registry.pt
plone/introspector/browser/configure.zcml
plone/introspector/browser/handler.pt
plone/introspector/browser/info.pt
plone/introspector/browser/infoprovider.py
plone/introspector/browser/inspect.py
plone/introspector/browser/introspector.py
plone/introspector/browser/introspectorbrowse_view.pt
plone/introspector/browser/introspectorview.pt
plone/introspector/browser/minus.gif
plone/introspector/browser/mktree.css
plone/introspector/browser/mktree.js
plone/introspector/browser/plus.gif
plone/introspector/browser/search_registry.pt
plone/introspector/browser/subscription_adapter.pt
plone/introspector/browser/utils.pt
plone/introspector/browser/infoprovider_templates/workflow.pt
plone/introspector/tests/__init__.py
plone/introspector/tests/base.py
plone/introspector/tests/object_introspector.txt
plone/introspector/tests/registry_browse.txt
plone/introspector/tests/registry_search.txt
plone/introspector/tests/test_doc.py
plone/introspector/tests/workflowinfo.txt