Metadata-Version: 1.0
Name: plone.introspector
Version: 0.1
Summary: Introspection helpers for Zope and Plone.
Home-page: http://pypi.python.org/pypi/plone.introspector
Author: Martin Lundwall, Lennart Regebro
Author-email: martin@webworks.se
License: ZPL 2.1
Keywords: zope zope2 plone web introspection introspector
Platform: UNKNOWN
Classifier: Development Status :: 2 - Pre-Alpha
Classifier: Environment :: Web Environment
Classifier: Intended Audience :: Developers
Classifier: License :: OSI Approved :: Zope Public License
Classifier: Programming Language :: Python
Classifier: Natural Language :: English
Classifier: Operating System :: OS Independent
Classifier: Topic :: Internet :: WWW/HTTP
Classifier: Framework :: Zope3
